topsis_Tejasvi_102003367/__init__.py
topsis_Tejasvi_102003367/topsis_Tejasvi_102003367.py
topsis_Tejasvi_102003367-0.0.1.dist-info/METADATA
topsis_Tejasvi_102003367-0.0.1.dist-info/WHEEL
topsis_Tejasvi_102003367-0.0.1.dist-info/top_level.txt
topsis_Tejasvi_102003367-0.0.1.dist-info/RECORD
