Metadata-Version: 2.1
Name: topsis-Tejasvi-102003367
Version: 0.0.1
Summary: Topsis package
Home-page: UNKNOWN
Author: Tejasvi S Jain
Author-email: <tejasvisjain0214@gmail.com>
License: UNKNOWN
Keywords: python,topsis,machinelearning,datascience
Platform: UNKNOWN
Classifier: Development Status :: 1 - Planning
Classifier: Intended Audience :: Developers
Classifier: Programming Language :: Python :: 3
Classifier: Operating System :: Unix
Classifier: Operating System :: MacOS :: MacOS X
Classifier: Operating System :: Microsoft :: Windows
Requires-Dist: numpy
Requires-Dist: pandas
